LICENSE
README.md
polars_deunicode_string-0.2.6.dist-info/METADATA
polars_deunicode_string-0.2.6.dist-info/WHEEL
polars_deunicode_string-0.2.6.dist-info/licenses/LICENSE
polars_deunicode_string/__init__.py
polars_deunicode_string/_internal.abi3.so
polars_deunicode_string/_internal.pyi
polars_deunicode_string/typing.py
polars_deunicode_string-0.2.6.dist-info/RECORD
