Metadata-Version: 2.4
Name: polars-deunicode-string
Version: 0.2.6
Classifier: Programming Language :: Rust
Classifier: Programming Language :: Python :: Implementation :: CPython
Classifier: Programming Language :: Python :: Implementation :: PyPy
Requires-Dist: maturin>=1.7.6
Requires-Dist: mypy>=1.13.0
Requires-Dist: pytest>=8.3.3
Requires-Dist: ruff>=0.8.1
Requires-Dist: maturin[patchelf]
License-File: LICENSE
Summary: Polars plugin to decode strings.
Author-email: Orlando Reyes <eorlando.reyesruiz@gmail.com>
Requires-Python: >=3.8
Project-URL: Homepage, https://github.com/TheLionCoder/polars-deunicode-string
Project-URL: Repository, https://github.com/TheLionCoder/polars-deunicode-string
